emlineclipper/__init__.py
emlineclipper/emclip.py
emlineclipper-1.2.4.dist-info/LICENSE
emlineclipper-1.2.4.dist-info/METADATA
emlineclipper-1.2.4.dist-info/WHEEL
emlineclipper-1.2.4.dist-info/top_level.txt
emlineclipper-1.2.4.dist-info/RECORD
